JupyterReviewer/AnnotationDisplayComponent.py
JupyterReviewer/Data.py
JupyterReviewer/ReviewDataApp.py
JupyterReviewer/ReviewDataInterface.py
JupyterReviewer/ReviewerTemplate.py
JupyterReviewer/__init__.py
JupyterReviewer/AnnotationDisplayComponents/__init__.py
JupyterReviewer/AppComponents/CNVPlotComponent.py
JupyterReviewer/AppComponents/DataTableComponents.py
JupyterReviewer/AppComponents/MutationTableComponent.py
JupyterReviewer/AppComponents/PhylogicComponents.py
JupyterReviewer/AppComponents/__init__.py
JupyterReviewer/AppComponents/utils.py
JupyterReviewer/DataTypes/GenericData.py
JupyterReviewer/DataTypes/PatientSampleData.py
JupyterReviewer/DataTypes/__init__.py
JupyterReviewer/Reviewers/ExampleReviewer.py
JupyterReviewer/Reviewers/__init__.py
JupyterReviewer-0.0.5.dist-info/.ipynb_checkpoints/PKG-INFO-checkpoint
JupyterReviewer-0.0.5.dist-info/.ipynb_checkpoints/SOURCES-checkpoint.txt
JupyterReviewer-0.0.5.dist-info/.ipynb_checkpoints/requires-checkpoint.txt
JupyterReviewer-0.0.5.dist-info/.ipynb_checkpoints/top_level-checkpoint.txt
JupyterReviewer-0.0.5.dist-info/LICENSE.txt
JupyterReviewer-0.0.5.dist-info/METADATA
JupyterReviewer-0.0.5.dist-info/WHEEL
JupyterReviewer-0.0.5.dist-info/top_level.txt
JupyterReviewer-0.0.5.dist-info/RECORD
