Metadata-Version: 2.1
Name: JupyterReviewer
Version: 0.0.5
Summary: A general tool to create dashboards for manual review
Home-page: https://github.com/getzlab/JupyterReviewer
Author: Claudia Chu
Author-email: cchu@broadinstitute.org
Project-URL: Bug Tracker, https://github.com/getzlab/JupyterReviewer/issues
Classifier: Programming Language :: Python :: 3
Classifier: License :: OSI Approved :: MIT License
Classifier: Operating System :: OS Independent
Requires-Python: >=3.6
License-File: LICENSE.txt
Requires-Dist: cnv-suite
Requires-Dist: dash
Requires-Dist: dash-bootstrap-components
Requires-Dist: dash-cytoscape
Requires-Dist: dash-daq
Requires-Dist: fsspec
Requires-Dist: gcsfs
Requires-Dist: google-auth
Requires-Dist: google-api-core
Requires-Dist: hound
Requires-Dist: ipykernel
Requires-Dist: ipython
Requires-Dist: jupyter-dash
Requires-Dist: jupyterlab
Requires-Dist: matplotlib
Requires-Dist: pandas
Requires-Dist: pickleshare
Requires-Dist: pillow
Requires-Dist: pip
Requires-Dist: plotly
Requires-Dist: scipy
Requires-Dist: setuptools
Requires-Dist: flask (<=2.2.1)
Requires-Dist: werkzeug (<=2.2.1)
